{
  "uuid": "f94530ef-c47f-4dbd-91e5-8d6b589226c1",
  "name": "ls2",
  "details": "",
  "snapshots": [
    {
      "uuid": "965931d6-1f6d-410a-9f75-0ad1dac21b72",
      "isoStringDate": "2024-12-06T20:18:40.783Z",
      "products": [
        {
          "uuid": "d6e4bf34-05f8-4776-ab12-9ae5a95961a4",
          "sku": "LS2103521011.XL",
          "ids": [
            "9035210110050",
            "6958639485788"
          ],
          "details": "",
          "additions": [
            {
              "order": 1,
              "quantity": 1
            },
            {
              "order": 41,
              "quantity": 1
            },
            {
              "order": 77,
              "quantity": 1
            }
          ],
          "title": "352 ROOKIE MONO MATT BLACK XL"
        },
        {
          "uuid": "cb0382e0-fb52-488a-90ae-a509cc5d245f",
          "sku": "LS2103203192.L",
          "ids": [
            "1032031920040",
            "6958639486495"
          ],
          "details": "",
          "additions": [
            {
              "order": 2,
              "quantity": 1
            }
          ],
          "title": "FF320 ENTER NAVY BL/PU GS L BL"
        },
        {
          "uuid": "dabb6681-013a-477b-9d62-307c8e0a0e44",
          "sku": "LS2503701011.L",
          "ids": [
            "5037010110040",
            "6958639465841"
          ],
          "details": "",
          "additions": [
            {
              "order": 3,
              "quantity": 1
            }
          ],
          "title": "CASCO LS2 FF 370 EASY MATT BLACK L"
        },
        {
          "uuid": "8849dc2f-a00d-4342-a08c-0989bfa47826",
          "sku": "LS2503701011.M",
          "ids": [
            "5037010110030",
            "6958639465834"
          ],
          "details": "",
          "additions": [
            {
              "order": 4,
              "quantity": 1
            },
            {
              "order": 13,
              "quantity": 1
            }
          ],
          "title": "370 EASY MATT BLACK M"
        },
        {
          "uuid": "25fe18f1-8653-4c4c-830a-3e6db63e8c27",
          "sku": "LS2103534150.M",
          "ids": [
            "1035341500030",
            "6934432853788"
          ],
          "details": "",
          "additions": [
            {
              "order": 5,
              "quantity": 1
            },
            {
              "order": 62,
              "quantity": 1
            }
          ],
          "title": "CASCO MOTO LS2 FF353 RAPID NAUGHTY NARANJA-AZUL RPM925  AZUL OSCURO NAUGHTY M"
        },
        {
          "uuid": "c0a47c37-a412-4ebf-9983-2af3e6ce0664",
          "sku": "LS2103534150.L",
          "ids": [
            "1035341500040",
            "6934432853795"
          ],
          "details": "",
          "additions": [
            {
              "order": 6,
              "quantity": 1
            },
            {
              "order": 18,
              "quantity": 1
            }
          ],
          "title": "CASCO MOTO LS2 FF353 RAPID NAUGHTY NARANJA-AZUL RPM925  AZUL OSCURO NAUGHTY L"
        },
        {
          "uuid": "6c601548-321e-45af-a50d-06a94d243231",
          "sku": "LS2103533188.L",
          "ids": [
            "1035331880040",
            "6934432834350"
          ],
          "details": "",
          "additions": [
            {
              "order": 7,
              "quantity": 1
            },
            {
              "order": 14,
              "quantity": 1
            }
          ],
          "title": "CASCO LS2 353 RAPID KRUISE NEGRO GRIS L"
        },
        {
          "uuid": "21d56d64-64eb-40bb-ab91-5c9ad54ed0ae",
          "sku": "LS2103204011.L",
          "ids": [
            "1032040110040",
            "6934432831878"
          ],
          "details": "",
          "additions": [
            {
              "order": 8,
              "quantity": 1
            }
          ],
          "title": "320 EVO MONO MATT BLACK L"
        },
        {
          "uuid": "238ff227-1e58-4ffe-a9a4-0cf32f7bc0dd",
          "sku": "LS2103536131.XL",
          "ids": [
            "1035361310050",
            "6923221110638"
          ],
          "details": "",
          "additions": [
            {
              "order": 9,
              "quantity": 1
            },
            {
              "order": 11,
              "quantity": 1
            }
          ],
          "title": "CASCO LS2 353 XTREET RED XL"
        },
        {
          "uuid": "cf9fc087-75c4-444b-872c-7773742b1447",
          "sku": "LS2503701011.S",
          "ids": [
            "5037010110020",
            "6958639465827"
          ],
          "details": "",
          "additions": [
            {
              "order": 10,
              "quantity": 1
            }
          ],
          "title": "CASCO MOTO REBATIBLE LS2 370 EASY DOBLE VISOR NEGRO MATE RPM  NEGRO MATE EASY S"
        },
        {
          "uuid": "64281609-f503-4ffe-a9fa-c78b889fd95a",
          "sku": "LS2103533552.M",
          "ids": [
            "1035335520030",
            "6934432858271"
          ],
          "details": "",
          "additions": [
            {
              "order": 12,
              "quantity": 1
            }
          ],
          "title": "CASCO LS2 353 CIRCLE ORANGE M"
        },
        {
          "uuid": "40bb373c-30a6-43fb-bef4-fe5374fda9e5",
          "sku": "LS2903527303.M",
          "ids": [
            "9035273030030",
            "6958639486389"
          ],
          "details": "",
          "additions": [
            {
              "order": 15,
              "quantity": 1
            }
          ],
          "title": "CASCO INTEGRAL MOTO LS2 352 ROKIE STROKE ALERÓN SPOILER NARA"
        },
        {
          "uuid": "5c2c5b96-eafe-46e3-9047-d904ad2d322c",
          "sku": "LS2103536131.L",
          "ids": [
            "1035361310040",
            "6923221110621"
          ],
          "details": "",
          "additions": [
            {
              "order": 16,
              "quantity": 1
            }
          ],
          "title": "CASCO LS 353 XTREET RED L"
        },
        {
          "uuid": "ee0c1868-466d-41ba-b77b-02f0d6065c7a",
          "sku": "LS2103203192.M",
          "ids": [
            "1032031920030",
            "6958639486488"
          ],
          "details": "",
          "additions": [
            {
              "order": 17,
              "quantity": 1
            }
          ],
          "title": "FF320 ENTER NAVY BL/PU GS M BL"
        },
        {
          "uuid": "73e387ab-3e8f-4324-91f9-c80f1c765ecf",
          "sku": "LS2903527301.M",
          "ids": [
            "9035273010030",
            "6958639486327"
          ],
          "details": "",
          "additions": [
            {
              "order": 19,
              "quantity": 1
            }
          ],
          "title": "CASCO LS2 FF352 STROKE NEGRO GRIS"
        },
        {
          "uuid": "f986ab55-11a9-46b3-9780-5bd71d7eb57d",
          "sku": "LS2903527702.XL",
          "ids": [
            "9035277020050",
            "6958639487096"
          ],
          "details": "",
          "additions": [
            {
              "order": 20,
              "quantity": 1
            }
          ],
          "title": "LS2 FF 352 STINGER NEGRO SPOILER XL"
        },
        {
          "uuid": "9de7822a-101b-40a8-94b8-6b04902adaaf",
          "sku": "LS2103533188.XL",
          "ids": [
            "1035331880050",
            "6934432834367"
          ],
          "details": "",
          "additions": [
            {
              "order": 21,
              "quantity": 1
            }
          ],
          "title": "CASCO LS2 353 RAPID KRUISE NEGRO GRIS XL"
        },
        {
          "uuid": "1ad707c9-3d4d-4ce8-acc0-5702871b0fb4",
          "sku": "LS2103533552.S",
          "ids": [
            "1035335520020",
            "6934432858264"
          ],
          "details": "",
          "additions": [
            {
              "order": 22,
              "quantity": 1
            }
          ],
          "title": "LS2 353 CIRCLE FLUO ORANG S"
        },
        {
          "uuid": "8aac259b-8b66-465e-baf4-caac17554335",
          "sku": "LS2903527702.M",
          "ids": [
            "9035277020030",
            "6958639487072"
          ],
          "details": "",
          "additions": [
            {
              "order": 23,
              "quantity": 1
            }
          ],
          "title": "LS2 FF 352 STINGER NEGRO SPOILER M"
        },
        {
          "uuid": "785d3727-b906-42ec-9290-e930b46c4219",
          "sku": "LS2903521011.S",
          "ids": [
            "9035210110020",
            "6958639485757"
          ],
          "details": "",
          "additions": [
            {
              "order": 24,
              "quantity": 1
            },
            {
              "order": 25,
              "quantity": 1
            },
            {
              "order": 74,
              "quantity": 1
            }
          ],
          "title": "LS2 ROOKIE FF352 ALERON NEGRO MATE S"
        },
        {
          "uuid": "1d398917-0d94-4c20-a09e-2f0a1d3ff14d",
          "sku": "LS2903521011.2XL",
          "ids": [
            "9035210110060",
            "6958639485795"
          ],
          "title": "FF 352 rookie sploiler single mono matt black 2XL",
          "details": "No existe en contabilium",
          "additions": [
            {
              "order": 26,
              "quantity": 1
            },
            {
              "order": 33,
              "quantity": 1
            },
            {
              "order": 73,
              "quantity": 1
            }
          ]
        },
        {
          "uuid": "6f82ae80-39a6-4a53-9cc3-fbf0475cc3e7",
          "sku": "LS2168081006.L",
          "ids": [
            "1680810060040",
            "6923221185964"
          ],
          "details": "",
          "additions": [
            {
              "order": 27,
              "quantity": 1
            },
            {
              "order": 28,
              "quantity": 1
            }
          ],
          "title": "CASCO MOTO INTEGRAL LS2 STREAM II 808 NARDO GRIS RPM925"
        },
        {
          "uuid": "48974aa0-35b1-4314-98b6-2a4d0a3cb04e",
          "sku": "LS2935220436.S",
          "ids": [
            "9352204360020",
            "6958639486518"
          ],
          "details": "",
          "additions": [
            {
              "order": 29,
              "quantity": 1
            }
          ],
          "title": "CASCO INTEGRAL MOTO LS2 352 ROOKIE SKAR CON SPOILER - RPM925"
        },
        {
          "uuid": "cd0c9b9e-971a-4540-ae21-c7083fb0391a",
          "sku": "LS2168082311.XL",
          "ids": [
            "1680823110050",
            "6923221186534"
          ],
          "details": "",
          "additions": [
            {
              "order": 30,
              "quantity": 1
            },
            {
              "order": 59,
              "quantity": 1
            }
          ],
          "title": "CASCO MOTO DOBLE VISOR LS2 808 STREAM II ROAD AZUL MATE RPM"
        },
        {
          "uuid": "821b9a58-2358-4c6f-a3b9-27e84dfbda5b",
          "sku": "LS2168082311.M",
          "ids": [
            "1680823110030",
            "6923221186510"
          ],
          "details": "",
          "additions": [
            {
              "order": 31,
              "quantity": 1
            },
            {
              "order": 34,
              "quantity": 1
            }
          ],
          "title": "CASCO MOTO DOBLE VISOR LS2 808 STREAM II ROAD AZUL MATE RPM"
        },
        {
          "uuid": "b9be7396-adce-4ca1-931b-5de8dcb21cde",
          "sku": "LS2903521011.XS",
          "ids": [
            "9035210110010",
            "6958639485740"
          ],
          "details": "",
          "additions": [
            {
              "order": 32,
              "quantity": 1
            },
            {
              "order": 40,
              "quantity": 1
            },
            {
              "order": 71,
              "quantity": 1
            },
            {
              "order": 72,
              "quantity": 1
            },
            {
              "order": 83,
              "quantity": 1
            }
          ],
          "title": "FF 352 ROOKIE SPOILER SINGLE SOLID NEGRO MATE XS"
        },
        {
          "uuid": "a7b13ee6-5b6f-447a-b2ea-faa74273347c",
          "sku": "LS2168081006.M",
          "ids": [
            "1680810060030",
            "6923221185957"
          ],
          "details": "",
          "additions": [
            {
              "order": 35,
              "quantity": 1
            },
            {
              "order": 58,
              "quantity": 1
            }
          ],
          "title": "CASCO MOTO INTEGRAL LS2 STREAM II 808 NARDO GRIS RPM925"
        },
        {
          "uuid": "9ae27876-d429-4fe1-8fec-4e11fb833939",
          "sku": "LS2903527445.XL",
          "ids": [
            "9035274450050",
            "6958639487218"
          ],
          "details": "",
          "additions": [
            {
              "order": 36,
              "quantity": 1
            }
          ],
          "title": "LS2 FF 352 THUNDER BLANCO Y ROJO SPOILER XL"
        },
        {
          "uuid": "5f1f4f3c-3f55-411f-89cc-15d3ec566680",
          "sku": "LS2903527301.S",
          "ids": [
            "9035273010020",
            "6958639486310"
          ],
          "details": "",
          "additions": [
            {
              "order": 37,
              "quantity": 1
            },
            {
              "order": 54,
              "quantity": 1
            }
          ],
          "title": "CASCO LS2 FF352 STROKE NEGRO GRIS"
        },
        {
          "uuid": "936c8cad-ec74-4170-8fda-19104fe1a338",
          "sku": "LS2935220438.S",
          "ids": [
            "9352204380020",
            "6958639486655"
          ],
          "details": "",
          "additions": [
            {
              "order": 38,
              "quantity": 1
            }
          ],
          "title": "CASCO INTEGRAL MOTO LS2 352 ROOKIE MERCH MATE CON SPOILER"
        },
        {
          "uuid": "ae1b37ff-255b-484b-adbe-75b0c80b21bc",
          "sku": "LS2903527301.XL",
          "ids": [
            "9035273010050",
            "6958639486341"
          ],
          "details": "",
          "additions": [
            {
              "order": 39,
              "quantity": 1
            },
            {
              "order": 44,
              "quantity": 1
            }
          ],
          "title": "CASCO LS2 FF352 STROKE NEGRO GRIS"
        },
        {
          "uuid": "d6c42465-fcd0-48cb-be2a-224a48c88d5c",
          "sku": "LS2168082311.L",
          "ids": [
            "1680823110040",
            "6923221186527"
          ],
          "details": "",
          "additions": [
            {
              "order": 42,
              "quantity": 1
            },
            {
              "order": 50,
              "quantity": 1
            }
          ],
          "title": "CASCO MOTO DOBLE VISOR LS2 808 STREAM II ROAD AZUL MATE RPM"
        },
        {
          "uuid": "7d074590-434a-4869-bd7c-1ae0e3974787",
          "sku": "LS2935220438.XL",
          "ids": [
            "9352204380050",
            "6958639486686"
          ],
          "details": "",
          "additions": [
            {
              "order": 43,
              "quantity": 1
            }
          ],
          "title": "CASCO INTEGRAL MOTO LS2 352 ROOKIE MERCH MATE CON SPOILER"
        },
        {
          "uuid": "f4106bc5-7310-41f6-ae61-0fe5f329cd09",
          "sku": "LS2935220439.2X",
          "ids": [
            "9352204390060",
            "6958639486747"
          ],
          "details": "",
          "additions": [
            {
              "order": 45,
              "quantity": 1
            }
          ],
          "title": "CASCO INTEGRAL MOTO LS2 352 ROOKIE ULTRA ROJO BRILLO RPM925"
        },
        {
          "uuid": "528c7224-208d-4c1d-88ae-1e5ad5d9bff7",
          "sku": "LS2935220436.2X",
          "ids": [
            "9352204360060",
            "6958639486754"
          ],
          "details": "",
          "additions": [
            {
              "order": 46,
              "quantity": 1
            }
          ],
          "title": "CASCO INTEGRAL MOTO LS2 352 ROOKIE SKAR CON SPOILER - RPM925"
        },
        {
          "uuid": "d03a2281-90a0-4fb4-9dab-1b38bc57e1be",
          "sku": "LS2903527301.2X",
          "ids": [
            "9035273010060",
            "6958639486358"
          ],
          "details": "",
          "additions": [
            {
              "order": 47,
              "quantity": 1
            }
          ],
          "title": "CASCO INTEGRAL MOTO LS2 352 ROKIE STROKE ALERÓN SPOILER RPM"
        },
        {
          "uuid": "3d22d36f-862a-4c32-9ae1-74686133c41e",
          "sku": "LS2103203192.S",
          "ids": [
            "1032031920020",
            "6958639486471"
          ],
          "details": "",
          "additions": [
            {
              "order": 48,
              "quantity": 1
            }
          ],
          "title": "FF320 ENTER NAVY BL/PU GS S BL"
        },
        {
          "uuid": "8c7f411e-b820-400f-9beb-1b45e081689e",
          "sku": "LS2103204011.XL",
          "ids": [
            "1032040110050",
            "6934432831885"
          ],
          "details": "",
          "additions": [
            {
              "order": 49,
              "quantity": 1
            }
          ],
          "title": "320 EVO MONO MATT BLACK XL"
        },
        {
          "uuid": "a238973d-db09-4de2-bc81-476c82620462",
          "sku": "LS2103534150.S",
          "ids": [
            "1035341500020",
            "6934432853771"
          ],
          "details": "",
          "additions": [
            {
              "order": 51,
              "quantity": 1
            }
          ],
          "title": "CASCO MOTO LS2 FF353 RAPID NAUGHTY NARANJA-AZUL RPM925  AZUL OSCURO NAUGHTY S"
        },
        {
          "uuid": "90dac1c3-71de-47ee-95b0-5da7358df39c",
          "sku": "LS2903527303.S",
          "ids": [
            "9035273030020",
            "6958639486372"
          ],
          "details": "",
          "additions": [
            {
              "order": 52,
              "quantity": 1
            }
          ],
          "title": "CASCO INTEGRAL MOTO LS2 352 ROKIE STROKE ALERÓN SPOILER NARA"
        },
        {
          "uuid": "173a7c2a-77e3-4d08-8b3c-5ccf8d6b0323",
          "sku": "LS2168082245.XS",
          "ids": [
            "1680822450010",
            "6923221186428"
          ],
          "details": "",
          "additions": [
            {
              "order": 53,
              "quantity": 1
            }
          ],
          "title": "CASCO MOTO INTEGRAL DOBLE VISOR LS2 808 STREAM II JUNGLE RPM"
        },
        {
          "uuid": "38148f44-8e83-4483-80d7-2f8110142ae0",
          "sku": "LS2305625461.L",
          "ids": [
            "3056254610040",
            "6934432835302"
          ],
          "details": "",
          "additions": [
            {
              "order": 55,
              "quantity": 1
            }
          ],
          "title": "CASCO MOTO ABIERTO LS2 562 AIRFLOW CAMO GRIS AMARILLO RPM  TITANIO AMARILLO CAMO L"
        },
        {
          "uuid": "355b5613-b353-43f7-b825-50c1b4c2c084",
          "sku": "LS2305625232.M",
          "ids": [
            "3056252320030",
            "6934432838884"
          ],
          "details": "",
          "additions": [
            {
              "order": 56,
              "quantity": 1
            }
          ],
          "title": "CASCO MOTO ABIERTO 562 AIRFLOW CONDOR BLANCO NEGRO ROJO RPM  BLANCO AZUL Y ROJO CONDOR M"
        },
        {
          "uuid": "f2ab5dae-02ba-44f0-8451-867aa013a85c",
          "sku": "LS2305626025.L",
          "ids": [
            "3056260250040",
            "6923221116500"
          ],
          "details": "",
          "additions": [
            {
              "order": 57,
              "quantity": 1
            },
            {
              "order": 98,
              "quantity": 1
            }
          ],
          "title": "OF562 ANDROID BL/RD MT L"
        },
        {
          "uuid": "21bee0ce-ae1a-48ce-bda0-4ea044c293d8",
          "sku": "LS2168081006.XS",
          "ids": [
            "1680810060010",
            "6923221185933"
          ],
          "details": "",
          "additions": [
            {
              "order": 60,
              "quantity": 1
            }
          ],
          "title": "CASCO MOTO INTEGRAL LS2 STREAM II 808 NARDO GRIS RPM925"
        },
        {
          "uuid": "ec813618-6443-48a1-ba2b-ef6b014f6534",
          "sku": "LS2903527301.L",
          "ids": [
            "9035273010040",
            "6958639486334"
          ],
          "details": "",
          "additions": [
            {
              "order": 61,
              "quantity": 1
            }
          ],
          "title": "CASCO LS2 FF352 STROKE NEGRO GRIS"
        },
        {
          "uuid": "7afe9c27-db0e-45aa-8ed2-2a9694a8fc84",
          "sku": "LS2103233612.XS",
          "ids": [
            "1032336120010",
            "6934432833469"
          ],
          "details": "",
          "additions": [
            {
              "order": 63,
              "quantity": 1
            }
          ],
          "title": "CASCO MOTO INTEGRAL LS2 323 ARROW EVO TECHINO BLANCO / NEGRO"
        },
        {
          "uuid": "c45dcef7-db50-4fd6-afb7-9dcedc097807",
          "sku": "LS2404374032.XL",
          "ids": [
            "4043740320050",
            "6923221113462"
          ],
          "details": "",
          "additions": [
            {
              "order": 64,
              "quantity": 1
            }
          ],
          "title": "437 FAST STRIKE BLA-WHI-RED XL"
        },
        {
          "uuid": "57a773f9-392f-43d3-b57d-5de480c90148",
          "sku": "LS2404374032.L",
          "ids": [
            "4043740320040",
            "6923221113455"
          ],
          "details": "",
          "additions": [
            {
              "order": 65,
              "quantity": 1
            }
          ],
          "title": "437 FAST STRIKE BLA-WHI-RED L"
        },
        {
          "uuid": "07a943ee-9d6e-462c-85a8-17f69be254b2",
          "sku": "LS2404374032.S",
          "ids": [
            "4043740320020",
            "6923221113431"
          ],
          "details": "",
          "additions": [
            {
              "order": 66,
              "quantity": 1
            }
          ],
          "title": "437 FAST STRIKE BLA-WHI-RED S"
        },
        {
          "uuid": "ce24f26d-cd3e-4084-8033-fda33fb5f04d",
          "sku": "LS2509021011.M",
          "ids": [
            "5090210110030",
            "6934432859193"
          ],
          "details": "",
          "additions": [
            {
              "order": 67,
              "quantity": 1
            }
          ],
          "title": "CASCO MOTO REBATIBLE LS2 902 SCOPE NEGRO MATE PINLOCK RPM925"
        },
        {
          "uuid": "f97e5610-18c8-4eab-8160-95c9450a7bb8",
          "sku": "LS2903527303.2X",
          "ids": [
            "9035273030060",
            "6958639486419"
          ],
          "details": "",
          "additions": [
            {
              "order": 68,
              "quantity": 1
            }
          ],
          "title": "CASCO INTEGRAL MOTO LS2 352 ROKIE STROKE ALERÓN SPOILER NARA"
        },
        {
          "uuid": "61524ac1-81f3-48d8-a5dd-e99db8e66a1a",
          "sku": "LS2103533552.XL",
          "ids": [
            "1035335520050",
            "6934432858295"
          ],
          "details": "",
          "additions": [
            {
              "order": 69,
              "quantity": 1
            }
          ],
          "title": "CASCO LS2 353 CIRCLE FLOU ORANGE XL"
        },
        {
          "uuid": "ef191714-38dc-485e-8de2-fc05854f2e98",
          "sku": "LS2168081006.2X",
          "ids": [
            "1680810060060",
            "6923221185988"
          ],
          "details": "",
          "additions": [
            {
              "order": 70,
              "quantity": 1
            }
          ],
          "title": "CASCO MOTO INTEGRAL LS2 STREAM II 808 NARDO GRIS RPM925"
        },
        {
          "uuid": "4dbfaaeb-90bb-46c6-91cc-39ab2f937f58",
          "sku": "LS2103204011.2XL",
          "ids": [
            "1032040110060",
            "6934432831892"
          ],
          "title": "FF 320 stream evo matt black 2xl",
          "details": "crear publicacion",
          "additions": [
            {
              "order": 75,
              "quantity": 1
            }
          ]
        },
        {
          "uuid": "e032c806-fd7b-4b4c-b4d0-c8be32494d51",
          "sku": "LS2903521011.M",
          "ids": [
            "9035210110030",
            "6958639485764"
          ],
          "details": "",
          "additions": [
            {
              "order": 76,
              "quantity": 1
            }
          ],
          "title": "LS2 FF352 ROOKIE NEGRO MATE M"
        },
        {
          "uuid": "2e74fc39-4221-4c1f-b584-6b5bfbcc2d68",
          "sku": "LS2903521011.L",
          "ids": [
            "9035210110040",
            "6958639485771"
          ],
          "details": "",
          "additions": [
            {
              "order": 78,
              "quantity": 1
            },
            {
              "order": 82,
              "quantity": 1
            }
          ],
          "title": "LS2 FF352 ROOKIE NEGRO MATE L"
        },
        {
          "uuid": "2e974933-3330-4c80-9b49-675b27b012cc",
          "sku": "LS2103207079.XL",
          "ids": [
            "1032070790050",
            "6958639487447"
          ],
          "details": "",
          "additions": [
            {
              "order": 79,
              "quantity": 1
            }
          ],
          "title": "FF320 EVO MAX WH/RD GS XL BLANCO"
        },
        {
          "uuid": "c40cb93c-3822-4d0d-b45f-257e8f176719",
          "sku": "LS2103207082.2XL",
          "ids": [
            "1032070820060",
            "6958639485382"
          ],
          "details": "crear nuevo",
          "additions": [
            {
              "order": 80,
              "quantity": 1
            }
          ],
          "title": "FF320 EVO IMPACT BK/YL/B GS 2XL"
        },
        {
          "uuid": "a3165c3d-c19a-482d-b2f4-3165d80ef748",
          "sku": "LS2103527131.XX",
          "ids": [
            "1035271310060",
            "6934432811467"
          ],
          "details": "",
          "additions": [
            {
              "order": 81,
              "quantity": 1
            },
            {
              "order": 84,
              "quantity": 1
            }
          ],
          "title": "352 RECRUIT BLACK BLUE XX NORM"
        },
        {
          "uuid": "c95ecdfb-7558-498b-bdb8-8a8cea8d93ea",
          "sku": "LS2103233626.M",
          "ids": [
            "1032336260030",
            "6934432833575"
          ],
          "details": "",
          "additions": [
            {
              "order": 85,
              "quantity": 1
            }
          ],
          "title": "CASCO LS2 323 ARROW EVO BLANCO Y AZUL M"
        },
        {
          "uuid": "11bd482d-6d38-4b1a-9c43-fb6422339fbd",
          "sku": "LS2404374032.M",
          "ids": [
            "4043740320030",
            "6923221113448"
          ],
          "details": "",
          "additions": [
            {
              "order": 86,
              "quantity": 1
            }
          ],
          "title": "437 FAST STRIKE BLA-WHI-RED M"
        },
        {
          "uuid": "544332eb-c95b-4e09-a115-b304f0e82fc3",
          "sku": "LS2509021011.L",
          "ids": [
            "5090210110040",
            "6934432859209"
          ],
          "details": "",
          "additions": [
            {
              "order": 87,
              "quantity": 1
            }
          ],
          "title": "CASCO MOTO REBATIBLE LS2 902 SCOPE NEGRO MATE PINLOCK RPM925"
        },
        {
          "uuid": "926a6b02-fe4b-4a7d-9250-7b71b75c6792",
          "sku": "LS2103233613.L",
          "ids": [
            "1032336130040",
            "6934432833933"
          ],
          "details": "",
          "additions": [
            {
              "order": 88,
              "quantity": 1
            }
          ],
          "title": "CASCO LS2 323 EVO TEC NEGRO GRS Y VERDE L"
        },
        {
          "uuid": "5b4ecbe5-d6d4-4ddb-b9ab-7701f3e6883d",
          "sku": "LS2103233612.M",
          "ids": [
            "1032336120030",
            "6934432833483"
          ],
          "details": "",
          "additions": [
            {
              "order": 89,
              "quantity": 1
            }
          ],
          "title": "CASCO MOTO INTEGRAL LS2 323 EVO TECHNO RPM925  NEGRO-BLANCO ARROW M"
        },
        {
          "uuid": "a4ee0484-539b-42fb-9311-e6e1e10b67dd",
          "sku": "LS2103233098.M",
          "ids": [
            "1032330980030",
            "6958639495718"
          ],
          "details": "",
          "additions": [
            {
              "order": 90,
              "quantity": 1
            }
          ],
          "title": "CASCO MOTO CARBONO ARROW  C EVO 323 SOLID NEGRO RPM925   NEGRO ARROW M"
        },
        {
          "uuid": "1c013436-ad6b-490f-abda-89c904bf790e",
          "sku": "LS2103233098.L",
          "ids": [
            "1032330980040",
            "6958639495725"
          ],
          "details": "",
          "additions": [
            {
              "order": 91,
              "quantity": 1
            }
          ],
          "title": "CASCO MOTO CARBONO ARROW  C EVO 323 SOLID NEGRO RPM925   NEGRO ARROW L"
        },
        {
          "uuid": "235b7096-405e-4f62-abb3-380a193b9520",
          "sku": "LS2103233098.S",
          "ids": [
            "1032330980020",
            "6958639495701"
          ],
          "details": "",
          "additions": [
            {
              "order": 92,
              "quantity": 1
            }
          ],
          "title": "CASCO MOTO CARBONO ARROW  C EVO 323 SOLID NEGRO RPM925   NEGRO ARROW S"
        },
        {
          "uuid": "d8741e62-6c7d-43a2-af1e-a96a0f045da0",
          "sku": "LS2103233613.M",
          "ids": [
            "1032336130030",
            "6934432833926"
          ],
          "details": "",
          "additions": [
            {
              "order": 93,
              "quantity": 1
            }
          ],
          "title": "CASCO LS2 323 EVO TEC NEGRO GRIS Y VERDE M"
        },
        {
          "uuid": "5e259516-2014-438b-973e-8eea200a67f3",
          "sku": "LS2305626025.2XL",
          "ids": [
            "3056260250060",
            "6923221116524"
          ],
          "details": "",
          "additions": [
            {
              "order": 94,
              "quantity": 1
            }
          ],
          "title": "OF562 ANDROID BL/RD MT 2XL"
        },
        {
          "uuid": "992499d3-e4a2-4039-a75c-a9ef41856e8d",
          "sku": "LS2305625461.XL",
          "ids": [
            "3056254610050",
            "6934432835319"
          ],
          "details": "",
          "additions": [
            {
              "order": 95,
              "quantity": 1
            }
          ],
          "title": "562 AIRFLOW CAMO MATT TIT Y XL"
        },
        {
          "uuid": "6625a8c0-a706-4782-9c4d-d005208cf846",
          "sku": "LS2305626025.XL",
          "ids": [
            "3056260250050",
            "6923221116517"
          ],
          "details": "",
          "additions": [
            {
              "order": 96,
              "quantity": 1
            },
            {
              "order": 97,
              "quantity": 1
            }
          ],
          "title": "OF562 ANDROID BL/RD MT XL"
        },
        {
          "uuid": "ccb605ca-b7a0-4671-a0f6-4d492571e65f",
          "sku": "LS2305626025.M",
          "ids": [
            "3056260250030",
            "6923221116494"
          ],
          "details": "",
          "additions": [
            {
              "order": 99,
              "quantity": 1
            },
            {
              "order": 104,
              "quantity": 1
            }
          ],
          "title": "OF562 ANDROID BL/RD MT M"
        },
        {
          "uuid": "f3e4f054-44a0-49cb-ac92-f3b62129e26f",
          "sku": "LS2305625011.M",
          "ids": [
            "3056250110030",
            "6934432838747"
          ],
          "details": "",
          "additions": [
            {
              "order": 100,
              "quantity": 1
            },
            {
              "order": 107,
              "quantity": 1
            }
          ],
          "title": "562 AIRFLOW SOLID MATT BLACK M"
        },
        {
          "uuid": "515b379f-f8d6-4870-b6b4-7a7d140795bc",
          "sku": "LS2305625311.S",
          "ids": [
            "3056253110020",
            "6934432838808"
          ],
          "details": "",
          "additions": [
            {
              "order": 101,
              "quantity": 1
            }
          ],
          "title": "CASCO AIRFLOW METROPOLIS HVY 562 RPM925  NEGRO- AMARILLO AIRFLOW S"
        },
        {
          "uuid": "dae05fdd-f06d-4839-a7b9-94632d4101f0",
          "sku": "LS2305625311.XL",
          "ids": [
            "3056253110050",
            "6934432838839"
          ],
          "details": "",
          "additions": [
            {
              "order": 102,
              "quantity": 1
            }
          ],
          "title": "CASCO AIRFLOW METROPOLIS HVY 562 RPM925  NEGRO- AMARILLO AIRFLOW XL"
        },
        {
          "uuid": "78564916-6a0d-468a-909e-fbfe80e656be",
          "sku": "LS2305626025.S",
          "ids": [
            "3056260250020",
            "6923221116487"
          ],
          "details": "",
          "additions": [
            {
              "order": 103,
              "quantity": 1
            }
          ],
          "title": "OF562 ANDROID BL/RD MT S"
        },
        {
          "uuid": "c184da24-3617-47f3-a571-4e3cb76ad351",
          "sku": "LS2305625311.M",
          "ids": [
            "3056253110030",
            "6934432838815"
          ],
          "details": "",
          "additions": [
            {
              "order": 105,
              "quantity": 1
            }
          ],
          "title": "CASCO AIRFLOW METROPOLIS HVY 562 RPM925  NEGRO- AMARILLO AIRFLOW M"
        },
        {
          "uuid": "45d38ddd-b984-42a3-b86d-ae2bc939264c",
          "sku": "LS2305625011.L",
          "ids": [
            "3056250110040",
            "6934432838754"
          ],
          "details": "",
          "additions": [
            {
              "order": 106,
              "quantity": 1
            },
            {
              "order": 108,
              "quantity": 1
            }
          ],
          "title": "562 AIRFLOW SOLID MATT BLACK L"
        }
      ],
      "details": "con el nuevo ingreso del 4/12"
    }
  ]
}